{
    "title": "DeliveryNote Model",
    "type": "object",
    "properties": {
        "id": {
            "type": [
                "int"
            ],
            "optional": false
        },
        "customerOrderId": {
            "type": [
                "int",
                "null"
            ],
            "optional": true
        },
        "note": {
            "type": [
                "string",
                "null"
            ],
            "optional": true
        },
        "created": {
            "type": [
                "string",
                "null"
            ],
            "optional": true
        },
        "fulfillment": {
            "type": [
                "int",
                "null"
            ],
            "optional": true
        },
        "status": {
            "type": [
                "int",
                "null"
            ],
            "optional": true
        }
    },
    "required": [
        "id"
    ]
}