{
    "title": "TaxRate Model",
    "type": "object",
    "properties": {
        "id": {
            "type": [
                "string"
            ],
            "optional": false
        },
        "taxZoneId": {
            "type": [
                "string",
                "null"
            ],
            "optional": true
        },
        "taxClassId": {
            "type": [
                "string",
                "null"
            ],
            "optional": true
        },
        "rate": {
            "type": [
                "double",
                "null"
            ],
            "optional": true
        },
        "priority": {
            "type": [
                "int",
                "null"
            ],
            "optional": true
        }
    },
    "required": [
        "id"
    ]
}