{
    "title": "EmailTemplateI18n Model",
    "type": "object",
    "properties": {
        "emailTemplateId": {
            "type": [
                "string"
            ],
            "optional": true,
            "items": [
            ]
        },
        "localeName": {
            "type": [
                "string"
            ],
            "optional": true,
            "items": [
            ]
        },
        "subject": {
            "type": [
                "string",
                "null"
            ],
            "optional": true,
            "items": [
            ]
        },
        "contentHtml": {
            "type": [
                "string"
            ],
            "optional": true,
            "items": [
            ]
        },
        "contentText": {
            "type": [
                "string"
            ],
            "optional": true,
            "items": [
            ]
        },
        "pdf": {
            "type": [
                "string"
            ],
            "optional": true,
            "items": [
            ]
        },
        "filename": {
            "type": [
                "string"
            ],
            "optional": true,
            "items": [
            ]
        }
    },
    "required": [
    ]
}